dupan/__init__.py
dupan-0.1.dist-info/METADATA
dupan-0.1.dist-info/RECORD
dupan-0.1.dist-info/WHEEL
dupan-0.1.dist-info/top_level.txt
