Metadata-Version: 2.1
Name: dupan
Version: 0.1
Summary: manuplating baidu yun
Home-page: https://github.com/digglife/baidupan
Author: Zhu Sheng LI
Author-email: digglife@gmail.com
License: UNKNOWN
Platform: UNKNOWN
Classifier: Programming Language :: Python :: 3
Classifier: License :: OSI Approved :: MIT License
Classifier: Operating System :: OS Independent
